ds2g/TrackingService.py
ds2g/__init__.py
ds2g/__main__.py
ds2g-1.0.2.dist-info/LICENSE
ds2g-1.0.2.dist-info/METADATA
ds2g-1.0.2.dist-info/WHEEL
ds2g-1.0.2.dist-info/entry_points.txt
ds2g-1.0.2.dist-info/top_level.txt
ds2g-1.0.2.dist-info/RECORD
